xbotlib.py
xbotlib-0.16.1.dist-info/LICENSE
xbotlib-0.16.1.dist-info/WHEEL
xbotlib-0.16.1.dist-info/METADATA
xbotlib-0.16.1.dist-info/RECORD
