Metadata-Version: 2.1
Name: xbotlib
Version: 0.16.1
Summary: XMPP bots for humans
Home-page: https://git.autonomic.zone/decentral1se/xbotlib
License: GPLv3
Author: decentral1se
Author-email: d34ae261d3@sinenomine.email
Maintainer: decentral1se
Maintainer-email: d34ae261d3@sinenomine.email
Requires-Python: >=3.6,<4.0
Classifier: License :: Other/Proprietary License
Classifier: Programming Language :: Python :: 3
Classifier: Programming Language :: Python :: 3.6
Classifier: Programming Language :: Python :: 3.7
Classifier: Programming Language :: Python :: 3.8
Classifier: Programming Language :: Python :: 3.9
Provides-Extra: redis
Provides-Extra: web
Requires-Dist: Jinja2 (>=2.11.2,<3.0.0); extra == "web"
Requires-Dist: aiohttp (>=3.7.3,<4.0.0); extra == "web"
Requires-Dist: humanize (>=3.2.0,<4.0.0)
Requires-Dist: redis (>=3.5.3,<4.0.0); extra == "redis"
Requires-Dist: slixmpp (>=1.6.0,<2.0.0)
Project-URL: Repository, https://git.autonomic.zone/decentral1se/xbotlib
